{
  "type": "lesson",
  "id": "lesson-5",
  "title": "尾盤基礎：偶數理論",
  "positions": [
    {
      "title": "搶奇數空：尾盤",
      "meta": "棋局進行到最後，通常只剩下角落與X位、C位等等，這時候可以使用偶數理論來幫助思考\n\n如果沒有 PASS 的話，通常是由白棋下到最後一手，而一個局部最後下到的一方通常有較多的穩定子",
      "startTurn": "W",
      "startBoard": "..WWWWW./W.WWBW.W/WWBWWBWW/WBWWWWWW/WWWWWWBW/WWBWWBBW/W.WBWW.W/.WWWWWW.",
      "record": "b2a1b1h1g2h8g7a8b7",
      "comments": {
        "1": "偶數理論一開始是站在白棋這一邊的，白棋只需要找奇數空來下，甚至是下在X位都不會太差",
        "2": "黑棋拿到左上角之後，左上區域剩下一個空，又是一個奇數空",
        "3": "白棋繼續搶奇數空，下到最後一手之後翻轉的的棋子，對方不容易再翻轉",
        "4": "由於剩下的區域都是偶數空，因此黑棋無論往哪裡下，都會製造出奇數空，白棋只要緊跟著下即可",
        "5": "白棋繼續搶奇數空，下到最後一手",
        "9": "在這個極端例子，白棋僅靠偶數理論累積的穩定子，可以拿下勝利"
      }
    },
    {
      "title": "搶奇數空：中盤",
      "meta": "搶奇數空的情形不只在尾盤出現，中盤出現的奇數空也需要檢查是不是可以先搶",
      "startTurn": "W",
      "startBoard": "..BBBB../B.WWBB../BWBBWB../BWWWWB../BWWBWB../BBWWWB../......../........",
      "record": "b2a1b1e7",
      "comments": {
        "1": "白棋此時搶奇數空",
        "2": "黑棋拿角正常",
        "3": "白棋下到局部最後一手，並且不會因此讓黑棋有爬邊的機會，因此搶奇數空成功",
        "4": "並且因為在左上角白棋比黑棋多下到一手，逼迫黑棋開始消耗外部的手數"
      }
    },
    {
      "title": "逆偶數：白棋不能下的奇數空",
      "meta": "而黑棋為了避免白棋藉由偶數理論得利，需要做出「逆偶數」。逆偶數通常來自其中一方的PASS，讓棋局變成黑棋下到最後一手\n\n左上與左下是三格空，而右上與右下是四格空\n根據偶數理論，應該要搶左上或左下的奇數空\n觀察可以發現，左上的奇數空雙方都可以下，而左下的奇數空只有黑棋下得進去",
      "startTurn": "B",
      "startBoard": "..BWWBBB/W.BWWBBB/WWWWWWBW/WBWBWWBW/WBWBWWBB/WWWWWBBB/W.WBBW../..WWWW..",
      "record": "b2a1b1g7h8h7g8b7a8b8",
      "comments": {
        "1": "黑棋應該搶的是左上角的奇數空，因為左下角要保留到最後才下，讓棋局其他地方都變成由黑棋收到最後一手",
        "3": "黑棋下到左上最後一手",
        "4": "由於白棋下不進左下的奇數空，被迫從偶數空下手",
        "7": "黑棋再次下到最後一手，並且因為現在白棋無處可下只能 PASS，再次輪到黑棋先搶左下的奇數空",
        "10": "黑棋藉由逆偶數取得勝利"
      }
    },
    {
      "title": "逆偶數：白棋不想下的奇數空",
      "meta": "TEST",
      "startTurn": "B",
      "startBoard": "..BWWBBB/W.BWWBBB/WWWWWWBW/WBWBWWBW/WBWBWWBB/WWWWWBBB/W.WBBW../..BWWB..",
      "record": "b2",
      "comments": {
        "1": "RRRRRRRRRRRRR"
      }
    },
    {
      "title": "逆偶數：黑棋不能下的偶數空",
      "meta": "TEST",
      "startTurn": "B",
      "startBoard": "...WWWBB/BWBWWWWW/BBBWWWWW/WWWWWWWW/WWWWWWWW/BBBBBBWB/WBBBBBW./BBBBBB..",
      "record": "g8a1c1b1h8h7",
      "comments": {
        "1": "RRRRRRRRRRRRR"
      }
    },
    {
      "title": "破逆偶數",
      "meta": "TEST",
      "startTurn": "B",
      "startBoard": ".BBWWBBB/BBBWWBBB/BBBWWBBB/WWWWWWWW/BBBBBBBB/BBBBBBBB/WBBBBB../BBBBBB..",
      "record": "g8h8a1g7h7",
      "comments": {
        "1": "RRRRRRRRRRRRR"
      }
    }
  ]
}
